xfntrwin/__init__.py
xfntrwin/command_line.py
xfntrwin/fit_ref.py
xfntrwin/flu_geometry_routines.py
xfntrwin/flu_routines_new.py
xfntrwin/fluorescence.py
xfntrwin/main.py
xfntrwin/mainwindow.py
xfntrwin/mplwidget.py
xfntrwin/post_install_cmd.py
xfntrwin/xr_ref.so
xfntrwin/GUI/err1.ui
xfntrwin/GUI/err2.ui
xfntrwin/GUI/err3.ui
xfntrwin/GUI/err4.ui
xfntrwin/GUI/flupara.ui
xfntrwin/GUI/formfactorDialog.ui
xfntrwin/GUI/gixsyspara.ui
xfntrwin/GUI/mainwindow.ui
xfntrwin/GUI/plotscale.ui
xfntrwin/GUI/ref_multiFit_par.ui
xfntrwin/GUI/refpara.ui
xfntrwin/GUI/refsave.ui
xfntrwin/GUI/refsyspara.ui
xfntrwin/GUI/rodpara.ui
xfntrwin-0.2.2.dist-info/LICENSE
xfntrwin-0.2.2.dist-info/METADATA
xfntrwin-0.2.2.dist-info/WHEEL
xfntrwin-0.2.2.dist-info/entry_points.txt
xfntrwin-0.2.2.dist-info/top_level.txt
xfntrwin-0.2.2.dist-info/RECORD
