Metadata-Version: 2.1
Name: xfntrwin
Version: 0.2.2
Summary: A software that analyzes xfntr data
Home-page: https://github.com/zhul9311/XFNTR-win.git
Author: Zhu Liang
Author-email: zliang8@uic.edu
License: UNKNOWN
Platform: UNKNOWN
Classifier: Programming Language :: Python :: 3
Classifier: License :: OSI Approved :: MIT License
Classifier: Operating System :: OS Independent
Requires-Python: >=3.6
Requires-Dist: pyqt5
Requires-Dist: scipy
Requires-Dist: matplotlib
Requires-Dist: lmfit
Requires-Dist: periodictable
